libFlame/__init__.py
pygame_flame-1.2.dist-info/METADATA
pygame_flame-1.2.dist-info/WHEEL
pygame_flame-1.2.dist-info/top_level.txt
pygame_flame-1.2.dist-info/RECORD
